telestes/__init__.py
telestes/networks/__init__.py
telestes/networks/architectures/linear.py
telestes/networks/architectures/transformer.py
telestes/networks/policy.py
telestes/networks/value.py
telestes/ppo/__init__.py
telestes/ppo/agent.py
telestes-0.1.6.dist-info/LICENSES/GPLv3.txt
telestes-0.1.6.dist-info/LICENSES/TPLv1.txt
telestes-0.1.6.dist-info/METADATA
telestes-0.1.6.dist-info/WHEEL
telestes-0.1.6.dist-info/RECORD
