Metadata-Version: 2.3
Name: telestes
Version: 0.1.6
Summary: transformer-based reinforcment learning agents.
License: DBEL 1.1
Author: Vasilis Valatsos
Author-email: aethrvmn@apotheke.earth
Requires-Python: >=3.13
Classifier: License :: Other/Proprietary License
Classifier: Programming Language :: Python :: 3
Classifier: Programming Language :: Python :: 3.13
Requires-Dist: numpy (>=2.2.5,<3.0.0)
Requires-Dist: torch (>=2.6.0,<3.0.0)
Requires-Dist: tqdm (>=4.67.1,<5.0.0)
